.gitignore
AUTHORS.rst
Changelog.rst
LICENSE
README.rst
setup.cfg
setup.py
djangopypi/__init__.py
djangopypi/admin.py
djangopypi/decorators.py
djangopypi/feeds.py
djangopypi/forms.py
djangopypi/http.py
djangopypi/models.py
djangopypi/search_indexes.py
djangopypi/settings.py
djangopypi/signals.py
djangopypi/urls.py
djangopypi/utils.py
djangopypi.egg-info/PKG-INFO
djangopypi.egg-info/SOURCES.txt
djangopypi.egg-info/dependency_links.txt
djangopypi.egg-info/not-zip-safe
djangopypi.egg-info/requires.txt
djangopypi.egg-info/top_level.txt
djangopypi/management/__init__.py
djangopypi/management/commands/__init__.py
djangopypi/management/commands/loadclassifiers.py
djangopypi/management/commands/ppadd.py
djangopypi/migrations/0001_initial.py
djangopypi/migrations/0002_refactoring.py
djangopypi/migrations/0003_add_masterindex_mirrorlog.py
djangopypi/migrations/0004_allow_anonymous_distributions.py
djangopypi/migrations/0005_allow_null_distribution_uploader.py
djangopypi/migrations/__init__.py
djangopypi/templates/djangopypi/base.html
djangopypi/templates/djangopypi/package_detail.html
djangopypi/templates/djangopypi/package_detail_simple.html
djangopypi/templates/djangopypi/package_doap.xml
djangopypi/templates/djangopypi/package_list.html
djangopypi/templates/djangopypi/package_list_simple.html
djangopypi/templates/djangopypi/package_manage.html
djangopypi/templates/djangopypi/package_manage_versions.html
djangopypi/templates/djangopypi/release_detail.html
djangopypi/templates/djangopypi/release_doap.xml
djangopypi/templates/djangopypi/release_doap_fragment.xml
djangopypi/templates/djangopypi/release_list.html
djangopypi/templates/djangopypi/release_manage.html
djangopypi/templates/djangopypi/release_manage_files.html
djangopypi/templates/djangopypi/release_upload_file.html
djangopypi/templates/djangopypi/haystack/package_text.txt
djangopypi/templatetags/__init__.py
djangopypi/templatetags/safemarkup.py
djangopypi/tests/__init__.py
djangopypi/tests/pip.py
djangopypi/views/__init__.py
djangopypi/views/distutils.py
djangopypi/views/packages.py
djangopypi/views/releases.py
djangopypi/views/xmlrpc.py