Metadata-Version: 1.0
Name: djangopypi
Version: 0.4.4
Summary: A Django application that emulates the Python Package Index.
Home-page: http://github.com/benliles/djangopypi
Author: Benjamin Liles
Author-email: benliles@gmail.com
License: BSD
Keywords: django pypi packaging index
Platform: UNKNOWN
Classifier: Framework :: Django
Classifier: Development Status :: 4 - Beta
Classifier: Programming Language :: Python
Classifier: Environment :: Web Environment
Classifier: Operating System :: OS Independent
Classifier: Intended Audience :: Developers
Classifier: Intended Audience :: System Administrators
Classifier: License :: OSI Approved :: BSD License
Classifier: Topic :: System :: Software Distribution
Classifier: Programming Language :: Python
Classifier: Topic :: Software Development :: Libraries :: Python Modules
